setup.py
maydist/Binomialdistribution.py
maydist/Gaussiandistribution.py
maydist/Generaldistribution.py
maydist/__init__.py
maydist.egg-info/PKG-INFO
maydist.egg-info/SOURCES.txt
maydist.egg-info/dependency_links.txt
maydist.egg-info/not-zip-safe
maydist.egg-info/top_level.txt